smartcleaner/__init__.py
smartcleaner/core.py
smartcleaner-0.1.0.dist-info/licenses/LICENSE
smartcleaner-0.1.0.dist-info/METADATA
smartcleaner-0.1.0.dist-info/WHEEL
smartcleaner-0.1.0.dist-info/top_level.txt
smartcleaner-0.1.0.dist-info/RECORD
