Metadata-Version: 2.4
Name: smartcleaner
Version: 0.1.0
Summary: Smart auto-cleaning tool for Pandas DataFrames
Author: Vishwa
Requires-Python: >=3.8
License-File: LICENSE
Requires-Dist: pandas
Requires-Dist: numpy
Requires-Dist: scipy
Dynamic: author
Dynamic: license-file
Dynamic: requires-dist
Dynamic: requires-python
Dynamic: summary
